{
    "Abas": 100,
    "Abbas": 1600,
    "Abdul": 400,
    "Abdulla": 400,
    "Abuzar": 100,
    "Adel": 400,
    "Adil": 3600,
    "Afgan": 100,
    "Aftandil": 100,
    "Aghasi": 400,
    "Agil": 900,
    "Agshin": 1600,
    "Ahmed": 400,
    "Aitan": 100,
    "Akif": 2500,
    "Akim": 100,
    "Akper": 900,
    "Akram": 400,
    "Aladdin": 900,
    "Albert": 900,
    "Alekper": 1600,
    "Aleksandr": 2500,
    "Aleksey": 1600,
    "Alen": 400,
    "Alex": 3600,
    "Alexander": 3600,
    "Alexandr": 400,
    "Alexej": 400,
    "Alexey": 1600,
    "Ali": 4900,
    "Alibay": 900,
    "Alik": 3600,
    "Alisher": 400,
    "Altay": 400,
    "Alv": 100,
    "Amir": 400,
    "Anar": 6400,
    "Anatoly": 900,
    "Andrey": 400,
    "Anvar": 400,
    "Aqil": 400,
    "Aram": 900,
    "Araz": 900,
    "Arif": 3600,
    "Arkadiy": 400,
    "Arslan": 400,
    "Artur": 900,
    "Asad": 900,
    "Asadulla": 100,
    "Asif": 3600,
    "Asim": 400,
    "Asker": 400,
    "Aslan": 900,
    "Avag": 400,
    "Ayan": 900,
    "Ayaz": 400,
    "Aydin": 3600,
    "Ayhan": 400,
    "Aykhan": 900,
    "Azad": 900,
    "Azer": 6400,
    "Azim": 900,
    "Aziz": 2500,
    "Baba": 100,
    "Bakhtiyar": 900,
    "Bayram": 400,
    "Behruz": 400,
    "Beybala": 100,
    "Beyukaga": 100,
    "Boris": 1600,
    "Cahangir": 900,
    "Cavid": 900,
    "Cemshid": 100,
    "Ceyhun": 2500,
    "Chingiz": 3600,
    "Dadash": 100,
    "Daniel": 900,
    "David": 900,
    "Davud": 900,
    "Denis": 900,
    "Dima": 2500,
    "Dmitri": 900,
    "Dmitriy": 1600,
    "Dmitry": 400,
    "Edik": 400,
    "Eduard": 1600,
    "Efqan": 100,
    "Ekber": 400,
    "Elbrus": 100,
    "Elchin": 6400,
    "Elcin": 2500,
    "Eldar": 6400,
    "Elfan": 100,
    "Elik": 100,
    "Elkhan": 3600,
    "Elman": 3600,
    "Elmar": 3600,
    "Elnur": 4900,
    "Elshad": 3600,
    "Elshan": 4900,
    "Eltaj": 100,
    "Eltay": 100,
    "Elton": 100,
    "Elvin": 1600,
    "Elxan": 2500,
    "Emil": 4900,
    "Emin": 6400,
    "Enrik": 100,
    "Enver": 900,
    "Erik": 400,
    "Ernest": 400,
    "Etibar": 2500,
    "Etimad": 100,
    "Evgeny": 900,
    "Eynulla": 900,
    "Fagan": 1600,
    "Faig": 1600,
    "Faik": 1600,
    "Faiq": 900,
    "Fair": 100,
    "Fakhraddin": 100,
    "Farda": 100,
    "Farhad": 2500,
    "Farid": 6400,
    "Fariz": 100,
    "Farman": 400,
    "Farrukh": 400,
    "Fazil": 400,
    "Fedor": 400,
    "Feliks": 1600,
    "Fikret": 1600,
    "Fuad": 6400,
    "Gabil": 900,
    "Gahraman": 100,
    "Gamlet": 400,
    "Garik": 400,
    "Gasan": 900,
    "Gena": 400,
    "Gennady": 400,
    "Goshgar": 100,
    "Grigori": 400,
    "Gulam": 400,
    "Gultekin": 100,
    "Gunay": 2500,
    "Gurban": 2500,
    "Habib": 900,
    "Haci": 400,
    "Hafiz": 3600,
    "Hasan": 400,
    "Hassan": 400,
    "Heydar": 900,
    "Hidayet": 400,
    "Hikmet": 400,
    "Huseyn": 1600,
    "Hussein": 400,
    "Ibrahim": 400,
    "Igbal": 100,
    "Igor": 3600,
    "Ilgar": 4900,
    "Ilham": 4900,
    "Ilia": 400,
    "Ilkin": 3600,
    "Ilmar": 100,
    "Ilqar": 1600,
    "Ilya": 2500,
    "Ilyas": 400,
    "Imran": 1600,
    "Iosif": 900,
    "Isa": 2500,
    "Isabala": 100,
    "Isak": 100,
    "Iskander": 400,
    "Iskender": 400,
    "Islam": 1600,
    "Ismael": 400,
    "Ismail": 900,
    "Ismayil": 900,
    "Ivan": 400,
    "Jabbar": 400,
    "Jafar": 1600,
    "Jakov": 400,
    "Jalal": 400,
    "Jamal": 2500,
    "Jamil": 900,
    "Jamshid": 400,
    "Javid": 2500,
    "Jeyhun": 3600,
    "John": 400,
    "Juri": 900,
    "Jurij": 400,
    "Kamal": 1600,
    "Kamil": 2500,
    "Kamran": 4900,
    "Karen": 900,
    "Kazbek": 400,
    "Kenan": 3600,
    "Kerim": 400,
    "Khalig": 100,
    "Khasim": 100,
    "Khayal": 2500,
    "Konstantin": 1600,
    "Leonid": 2500,
    "Lev": 900,
    "Magomed": 400,
    "Mahir": 3600,
    "Mahmud": 400,
    "Makhmud": 100,
    "Maksud": 1600,
    "Malkhaz": 400,
    "Mamed": 1600,
    "Manaf": 400,
    "Mansur": 400,
    "Mark": 1600,
    "Matan": 100,
    "Maxim": 400,
    "Megsed": 100,
    "Mehdi": 1600,
    "Mehman": 2500,
    "Michail": 2500,
    "Mihail": 1600,
    "Mikail": 900,
    "Mikayil": 900,
    "Mikhail": 1600,
    "Mirza": 1600,
    "Mishel": 100,
    "Mizir": 100,
    "Movlud": 100,
    "Mowlud": 100,
    "Mubariz": 2500,
    "Mukhtar": 400,
    "Murad": 4900,
    "Musa": 2500,
    "Muslum": 100,
    "Mustafa": 2500,
    "Myron": 100,
    "Nadir": 900,
    "Nail": 400,
    "Nakim": 100,
    "Namig": 3600,
    "Namik": 3600,
    "Namiq": 900,
    "Namus": 900,
    "Nariman": 400,
    "Nasib": 100,
    "Nasim": 900,
    "Nasir": 400,
    "Nasreddin": 400,
    "Natig": 2500,
    "Natik": 1600,
    "Natiq": 1600,
    "Nazim": 4900,
    "Neriman": 400,
    "Nicat": 1600,
    "Nihat": 400,
    "Nikolaj": 400,
    "Nikolay": 400,
    "Niyamaddin": 900,
    "Niyazi": 400,
    "Nizami": 2500,
    "Nodar": 400,
    "Nuri": 400,
    "Nurlan": 900,
    "Nurulla": 100,
    "Oktay": 1600,
    "Oleg": 4900,
    "Omar": 400,
    "Orkhan": 3600,
    "Orxan": 3600,
    "Parviz": 2500,
    "Pavel": 400,
    "Perviz": 1600,
    "Piotr": 400,
    "Polad": 2500,
    "Qadir": 400,
    "Rafael": 2500,
    "Rafail": 1600,
    "Rafat": 400,
    "Rafi": 400,
    "Rafig": 1600,
    "Rafik": 1600,
    "Rafiq": 900,
    "Rahid": 100,
    "Rahim": 900,
    "Rahman": 400,
    "Rail": 400,
    "Rajab": 900,
    "Ramazan": 400,
    "Ramil": 3600,
    "Ramin": 3600,
    "Ramiz": 3600,
    "Ramzi": 2500,
    "Raphael": 400,
    "Rashad": 4900,
    "Rashid": 2500,
    "Rasim": 3600,
    "Rauf": 6400,
    "Resat": 400,
    "Riad": 400,
    "Riyad": 400,
    "Robert": 900,
    "Roma": 900,
    "Romal": 100,
    "Roman": 3600,
    "Rovnak": 100,
    "Rovshan": 4900,
    "Rowschan": 3600,
    "Rufat": 4900,
    "Ruslan": 4900,
    "Rustam": 3600,
    "Rustem": 400,
    "Sabir": 1600,
    "Sabit": 400,
    "Sadig": 400,
    "Sahib": 1600,
    "Saleem": 400,
    "Salim": 400,
    "Salman": 900,
    "Salmi": 100,
    "Samir": 6400,
    "Sascha": 900,
    "Sasha": 900,
    "Sebuhi": 100,
    "Senan": 100,
    "Serge": 100,
    "Sergei": 1600,
    "Sergej": 900,
    "Sergey": 4900,
    "Servat": 100,
    "Seyidaga": 100,
    "Seymur": 2500,
    "Shaban": 100,
    "Shahin": 3600,
    "Shakhriyar": 100,
    "Shamil": 2500,
    "Stanislav": 900,
    "Stas": 400,
    "Sultan": 400,
    "Sunay": 400,
    "Tahir": 3600,
    "Tair": 900,
    "Talat": 400,
    "Talib": 400,
    "Tamerlan": 1600,
    "Tarlan": 4900,
    "Teimur": 900,
    "Telman": 400,
    "Tengiz": 400,
    "Teymur": 3600,
    "Timur": 2500,
    "Tofik": 900,
    "Togrul": 900,
    "Tural": 3600,
    "Turan": 3600,
    "Ulvi": 2500,
    "Vadim": 3600,
    "Vagif": 3600,
    "Vahid": 1600,
    "Valentin": 400,
    "Valeri": 400,
    "Valeriy": 400,
    "Valery": 900,
    "Vasif": 2500,
    "Victor": 900,
    "Vidadi": 1600,
    "Viktor": 400,
    "Vilayat": 100,
    "Vitali": 900,
    "Vitaliy": 2500,
    "Vjacheslav": 400,
    "Vlad": 100,
    "Vladimir": 3600,
    "Vladislav": 900,
    "Vugar": 6400,
    "Vuqar": 3600,
    "Vusal": 2500,
    "Vyacheslav": 900,
    "Yakov": 400,
    "Yalchin": 900,
    "Yan": 900,
    "Yaroslav": 400,
    "Yashar": 3600,
    "Yevgeny": 400,
    "Yunis": 400,
    "Yura": 900,
    "Yuri": 2500,
    "Yuriy": 400,
    "Yusif": 2500,
    "Zabil": 900,
    "Zafer": 400,
    "Zahid": 900,
    "Zakir": 2500,
    "Zaman": 400,
    "Zamig": 100,
    "Zamin": 400,
    "Zaur": 6400,
    "Ziya": 400,
    "Zohrab": 900
}