{
    "Aave": 400,
    "Ade": 100,
    "Adeele": 100,
    "Adriana": 100,
    "Agle": 100,
    "Agne": 1600,
    "Aida": 100,
    "Aide": 400,
    "Aiki": 100,
    "Aile": 900,
    "Aili": 3600,
    "Aima": 100,
    "Aime": 2500,
    "Aimi": 100,
    "Aina": 400,
    "Aino": 3600,
    "Aire": 1600,
    "Airi": 2500,
    "Airo": 100,
    "Aita": 1600,
    "Aive": 900,
    "Aivi": 2500,
    "Aivo": 3600,
    "Aleksandra": 1600,
    "Alexandra": 100,
    "Aljona": 400,
    "Alla": 900,
    "Alli": 100,
    "Alma": 100,
    "Alviina": 100,
    "Alvina": 100,
    "Amelija": 100,
    "Anastasija": 100,
    "Ande": 100,
    "Andra": 100,
    "Anette": 400,
    "Anfisa": 100,
    "Angela": 1600,
    "Angeliina": 100,
    "Angelika": 100,
    "Anita": 1600,
    "Anjuta": 100,
    "Ann": 1600,
    "Anna": 3600,
    "Anne": 6400,
    "Annela": 400,
    "Anneli": 4900,
    "Anne-Ly": 1600,
    "Annely": 1600,
    "Annemari": 400,
    "Anni": 2500,
    "Annika": 4900,
    "Antonija": 100,
    "Antonina": 400,
    "Anu": 6400,
    "An\u017eela": 100,
    "An\u017eelika": 400,
    "Asta": 2500,
    "Astra": 100,
    "Astrid": 900,
    "Astrit": 100,
    "Auli": 400,
    "Aulika": 400,
    "Aune": 400,
    "Auri": 100,
    "Ave": 3600,
    "Aveli": 100,
    "Avemari": 100,
    "Baiba": 400,
    "Banga": 100,
    "Berit": 400,
    "Birgit": 2500,
    "Carmen": 900,
    "Cecilija": 100,
    "Christel": 400,
    "Christine": 400,
    "Dagi": 100,
    "Dagmar": 400,
    "Dairi": 100,
    "Daisy": 100,
    "Deivi": 400,
    "Delia": 100,
    "Diaana": 100,
    "Diana": 3600,
    "Doris": 400,
    "Ebe": 100,
    "Eda": 2500,
    "Edda": 400,
    "Ede": 1600,
    "Edith": 400,
    "Eelika": 100,
    "Eesi": 400,
    "Eevi": 400,
    "Ege": 100,
    "Egle": 1600,
    "Egne": 100,
    "Eha": 4900,
    "Ehtel": 100,
    "Eigo": 400,
    "Eila": 100,
    "Eili": 400,
    "Eilike": 100,
    "Einike": 100,
    "Eivor": 100,
    "Elbe": 100,
    "Ele": 100,
    "Elen": 400,
    "Elena": 2500,
    "Eleri": 100,
    "Eleriin": 900,
    "Elga": 100,
    "Eli": 100,
    "Eliis": 400,
    "Elin": 400,
    "Elina": 1600,
    "Elise": 100,
    "Elle": 2500,
    "Ellen": 2500,
    "Elli": 100,
    "Ellu": 100,
    "Elve": 400,
    "Elvi": 900,
    "Elviira": 400,
    "Elviire": 100,
    "Elvina": 100,
    "Emma": 400,
    "Endla": 1600,
    "Ene": 6400,
    "Eneli": 100,
    "Enely": 100,
    "Epp": 3600,
    "Erda": 100,
    "Erika": 2500,
    "Erla": 100,
    "Erna": 400,
    "Esta": 900,
    "Ester": 2500,
    "Ethel": 400,
    "Eti": 100,
    "Eva": 3600,
    "Eve": 3600,
    "Eveli": 900,
    "Evelin": 2500,
    "Evelina": 100,
    "Evely": 900,
    "Evelyn": 1600,
    "Evi": 1600,
    "Evita": 100,
    "Fanna": 100,
    "Felita": 100,
    "Gaisa": 100,
    "Galina": 3600,
    "Garmen": 100,
    "Gea": 100,
    "Geidi": 400,
    "Gerda": 400,
    "Gerli": 1600,
    "Gerly": 100,
    "Grete": 100,
    "Haidi": 100,
    "Hanna": 400,
    "Heidi": 2500,
    "Heili": 900,
    "Heima": 100,
    "Heini": 1600,
    "Heivi": 100,
    "Hele": 900,
    "Helen": 3600,
    "Helena": 2500,
    "Heleri": 900,
    "Heli": 4900,
    "Helin": 400,
    "Helina": 2500,
    "Helis": 400,
    "Helje": 100,
    "Heljo": 900,
    "Helju": 2500,
    "Helle": 3600,
    "Helma": 100,
    "Helve": 2500,
    "Helvi": 400,
    "Here": 100,
    "Herle": 100,
    "Hiie": 1600,
    "Hilda": 400,
    "Hilja": 400,
    "Hilje": 100,
    "Hille": 900,
    "Iiris": 100,
    "Iivi": 400,
    "Ille": 900,
    "Illi": 100,
    "Ilme": 2500,
    "Ilona": 2500,
    "Ilvi": 400,
    "Imbi": 3600,
    "Ines": 400,
    "Inga": 2500,
    "Inge": 1600,
    "Ingrid": 3600,
    "Ingrit": 900,
    "Inna": 1600,
    "Inta": 100,
    "Ira": 900,
    "Ireen": 100,
    "Iren": 100,
    "Irene": 100,
    "Irina": 6400,
    "Irja": 100,
    "Irma": 100,
    "Ivi": 1600,
    "Ivika": 900,
    "Jaana": 1600,
    "Jaanika": 2500,
    "Jana": 3600,
    "Jane": 3600,
    "Janely": 400,
    "Janika": 900,
    "Janita": 100,
    "Janne": 1600,
    "Jekaterina": 100,
    "Jelena": 4900,
    "Jelizaveta": 100,
    "Jevgenia": 900,
    "Johanna": 400,
    "Julia": 3600,
    "June": 100,
    "Juta": 2500,
    "Juuli": 100,
    "Kaari": 1600,
    "Kaarin": 100,
    "Kadi": 2500,
    "Kadri": 4900,
    "K\u00e4rt": 1600,
    "K\u00e4tli": 100,
    "K\u00e4tlin": 2500,
    "Kai": 2500,
    "Kaia": 2500,
    "Kaidi": 2500,
    "Kaidy": 100,
    "Kaie": 2500,
    "Kaija": 100,
    "Kaili": 900,
    "Kaire": 3600,
    "Kairi": 3600,
    "Kairit": 900,
    "Kaisa": 900,
    "Kaisi": 100,
    "Kaisy": 100,
    "Kaja": 4900,
    "Kalvi": 400,
    "Karen": 100,
    "Kari": 100,
    "Karin": 4900,
    "Karit": 100,
    "Karita": 100,
    "Karmen": 1600,
    "Karolin": 100,
    "Katalin": 100,
    "Katariina": 100,
    "Katarin": 100,
    "Kathrine": 100,
    "Kati": 3600,
    "Katja": 400,
    "Katre": 2500,
    "Katri": 1600,
    "Katrin": 6400,
    "Katrina": 100,
    "Keit": 400,
    "Keiu": 100,
    "Kelli": 400,
    "Kelly": 1600,
    "Kerle": 400,
    "Kerli": 2500,
    "Kerly": 400,
    "Kersti": 4900,
    "Kert": 1600,
    "Kerti": 100,
    "Kertu": 900,
    "Ketlin": 100,
    "Ketrin": 100,
    "Kiira": 100,
    "Kina": 100,
    "Kirsti": 400,
    "Kirti": 400,
    "Koidula": 100,
    "Krete": 100,
    "Krista": 3600,
    "Kristel": 3600,
    "Kristi": 4900,
    "Kristiina": 3600,
    "Kristiine": 100,
    "Kristin": 900,
    "Kristina": 3600,
    "Kristjaana": 100,
    "Kristy": 400,
    "Kr\u00f5\u00f5t": 100,
    "Krystin": 100,
    "Ksenija": 400,
    "K\u00fclle": 100,
    "K\u00fclli": 4900,
    "K\u00fcllike": 1600,
    "K\u00fclliki": 100,
    "Lada": 100,
    "Laili": 400,
    "Laine": 2500,
    "Laivi": 100,
    "Larisa": 1600,
    "Larissa": 3600,
    "Laura": 3600,
    "Lea": 4900,
    "Leelo": 400,
    "Leena": 400,
    "Lehte": 400,
    "Lehti": 100,
    "Leida": 900,
    "Leili": 1600,
    "Leivi": 100,
    "Lelet": 100,
    "Lelija": 100,
    "Lemmi": 400,
    "Leoniida": 100,
    "Lia": 900,
    "Liane": 100,
    "Lianne": 100,
    "Lii": 1600,
    "Liia": 2500,
    "Liidia": 900,
    "Liilia": 900,
    "Liina": 4900,
    "Liis": 4900,
    "Liisa": 3600,
    "Liisbet": 100,
    "Liisi": 1600,
    "Liive": 100,
    "Liivi": 3600,
    "Liivia": 400,
    "Lili": 100,
    "Lilia": 3600,
    "Lilian": 2500,
    "Lilja": 100,
    "Liljan": 100,
    "Lille": 100,
    "Lilli": 100,
    "Lily": 400,
    "Linda": 400,
    "Ljubov": 400,
    "Ljudmila": 3600,
    "Ljudmilla": 400,
    "Loore": 100,
    "Lota": 100,
    "Ludmilla": 1600,
    "Ludviine": 100,
    "Luule": 1600,
    "Ly": 2500,
    "Lydia": 400,
    "Maaja": 400,
    "Maarika": 1600,
    "Maaris": 100,
    "Maarit": 100,
    "Maarja": 2500,
    "Made": 400,
    "Madli": 900,
    "Mae": 400,
    "Magi": 100,
    "Mai": 2500,
    "Maia": 900,
    "Maie": 4900,
    "Maigi": 400,
    "Maiken": 100,
    "Maiki": 100,
    "Maikki": 100,
    "Maila": 1600,
    "Maile": 100,
    "Maili": 400,
    "Mailis": 100,
    "Maimo": 400,
    "Maimu": 1600,
    "Maire": 3600,
    "Mairi": 900,
    "Mairit": 100,
    "Maiu": 400,
    "Maive": 400,
    "Mall": 2500,
    "Malle": 4900,
    "Mare": 4900,
    "Marelle": 400,
    "Maret": 3600,
    "Margarita": 1600,
    "Marge": 3600,
    "Margit": 3600,
    "Margo": 1600,
    "Margot": 400,
    "Mari": 4900,
    "Maria": 3600,
    "Mariaana": 100,
    "Mariann": 900,
    "Marianna": 100,
    "Marianne": 1600,
    "Marii": 100,
    "Mariin": 100,
    "Mariita": 100,
    "Marika": 4900,
    "Mariliis": 400,
    "Marilin": 1600,
    "Marina": 3600,
    "Maris": 3600,
    "Marit": 1600,
    "Marja": 900,
    "Marje": 3600,
    "Marju": 3600,
    "Marleen": 100,
    "Marlen": 100,
    "Marliis": 100,
    "Marta": 400,
    "Marti": 100,
    "Marve": 900,
    "Meeli": 1600,
    "Meelika": 400,
    "Meelike": 100,
    "Meeri": 100,
    "Megi": 100,
    "Meida": 100,
    "Meili": 400,
    "Merge": 400,
    "Merike": 4900,
    "Merili": 400,
    "Merilin": 1600,
    "Merily": 100,
    "Merit": 1600,
    "Merje": 1600,
    "Merle": 4900,
    "Merli": 900,
    "Merlin": 100,
    "Miia": 400,
    "Mikaela": 100,
    "Milja": 100,
    "Milla": 400,
    "Milve": 100,
    "Milvi": 2500,
    "Minija": 100,
    "Minni": 100,
    "Miraldine": 100,
    "Mirja": 100,
    "Mirjam": 1600,
    "Monika": 2500,
    "Moonika": 1600,
    "Nadezhda": 400,
    "Nastja": 100,
    "Natalia": 900,
    "Natalja": 4900,
    "Nele": 400,
    "Nelli": 400,
    "Niina": 2500,
    "Ninell": 100,
    "\u00d6nne": 400,
    "\u00d6rne": 400,
    "\u00d5ie": 400,
    "Oivi": 100,
    "Oksana": 1600,
    "Olga": 6400,
    "Olja": 100,
    "\u00d5lme": 100,
    "Paula": 100,
    "Piia": 1600,
    "Pille": 6400,
    "Pilvi": 900,
    "Piret": 4900,
    "Ragna": 100,
    "Ragne": 400,
    "Raili": 1600,
    "Raita": 100,
    "Rauna": 100,
    "Rea": 100,
    "Rebeka": 400,
    "Reeli": 400,
    "Reelika": 1600,
    "Reene": 100,
    "Reeni": 100,
    "Reesi": 100,
    "Reet": 4900,
    "Reeta": 100,
    "Regina": 2500,
    "Reili": 1600,
    "Reilika": 100,
    "Reini": 100,
    "Relija": 100,
    "Relika": 400,
    "Renee": 100,
    "Renna": 100,
    "Repina": 100,
    "Riin": 1600,
    "Riina": 6400,
    "Rimma": 100,
    "Rita": 2500,
    "Roseta": 100,
    "Rosete": 100,
    "Rumia": 100,
    "Ruth": 3600,
    "Rutt": 1600,
    "Rutti": 100,
    "Saale": 100,
    "Saima": 400,
    "Salle": 100,
    "Salme": 100,
    "Sandra": 900,
    "Sarmite": 400,
    "Sigle": 100,
    "Signe": 3600,
    "Sigrid": 900,
    "Siire": 100,
    "Siiri": 3600,
    "Siive": 100,
    "Silja": 2500,
    "Silje": 100,
    "Sille": 2500,
    "Silva": 900,
    "Silve": 100,
    "Silvi": 3600,
    "Silvia": 900,
    "Silvja": 100,
    "Sinaida": 100,
    "Siret": 1600,
    "Sirje": 6400,
    "Sirle": 400,
    "Sirlei": 100,
    "Sirli": 1600,
    "Sirlis": 100,
    "Sirly": 100,
    "Solvy": 100,
    "Suule": 100,
    "Svetlana": 4900,
    "Taima": 100,
    "Taimi": 1600,
    "Tairi": 100,
    "Taisi": 100,
    "Taisija": 100,
    "Taje": 100,
    "Tanja": 100,
    "Tatjana": 4900,
    "Tea": 1600,
    "Teele": 1600,
    "Teivi": 100,
    "Terje": 3600,
    "Thea": 400,
    "Tiia": 4900,
    "Tiina": 6400,
    "Tiiu": 4900,
    "Tiivi": 100,
    "Triin": 4900,
    "Triine": 100,
    "Triinu": 900,
    "Tuuli": 900,
    "\u00dclle": 6400,
    "Ulla": 400,
    "Ulvi": 900,
    "Ulvika": 100,
    "Urbe": 100,
    "Urve": 3600,
    "Urvi": 100,
    "Uusi": 100,
    "Vaida": 100,
    "Vaike": 3600,
    "Vaili": 100,
    "Vaimi": 100,
    "Valdi": 100,
    "Valentina": 1600,
    "Vally": 100,
    "Valve": 1600,
    "Valvi": 100,
    "Varje": 400,
    "Veera": 900,
    "Velli": 900,
    "Vera": 400,
    "Veronika": 1600,
    "Veroonika": 100,
    "Viia": 400,
    "Viiu": 2500,
    "Viive": 2500,
    "Viivi": 1600,
    "Viivika": 100,
    "Viktoria": 3600,
    "Vilja": 400,
    "Vilve": 400,
    "Vilvi": 100,
    "Virge": 1600,
    "Virve": 2500,
    "Vivika": 900,
    "\u017danete": 100,
    "Zinaida": 100,
    "Zinovia": 100
}